.codacy.yaml!
.coveralls.yml
.editorconfig
.gitignore
.pyup.yml
.travis.yml
AUTHORS.rst
CONTRIBUTING.rst
HISTORY.rst
LICENSE
MANIFEST.in
PITCHME.md
README.md
check_long_description.sh
coverall.sh
requirements.txt
setup.cfg
setup.py
tox.ini
upload_pypi.sh
usage.rst
doc/plot_fuzzy_numbers.py
doc/superellipse.png
doc/trapezoid.png
doc/triangle.png
doc/truncgennorm.png
doc/truncnorm.png
doc/uniform.png
doc/x+y.png
doc/x-y.png
doc/x:y.png
doc/x_mul_y.png
doc/x_pow_y.png
doc/x_pow_y_pdf_cdf.png
docs/Makefile
docs/authors.rst
docs/conf.py
docs/contributing.rst
docs/history.rst
docs/index.rst
docs/installation.rst
docs/lsdyna.rst
docs/make.bat
docs/readme.rst
docs/usage.rst
docs/_static/favicon.ico
docs/_static/style.css
docs/_templates/README.md
docs/_templates/layout.html
docs/examples/examples.rst
docs/examples/ssb/SimpSuppBeamPointLoad.png
docs/examples/ssb/ssb.png
docs/examples/ssb/ssb.py
docs/examples/ssb/ssb.rst
docs/examples/ssb/ssb_parameter.png
docs/operations/example_area.py
docs/operations/example_op.py
docs/operations/example_x2.py
docs/operations/example_x2_trapezoid.py
docs/operations/x+y.png
docs/operations/x-y.png
docs/operations/x:y.png
docs/operations/x_mul_y.png
docs/operations/x_pow_y.png
docs/phuzzy_api/Superellipse.png
docs/phuzzy_api/TruncGenNorm.png
docs/phuzzy_api/TruncNorm.png
docs/phuzzy_api/modules.rst
docs/phuzzy_api/phuzzy.mpl.rst
docs/phuzzy_api/phuzzy.rst
docs/phuzzy_api/phuzzy.shapes.rst
docs/phuzzy_api/phuzzy.shapes.superellipse.rst
docs/phuzzy_api/phuzzy.shapes.truncnorm.rst
docs/shapes/example_op_x.py
docs/shapes/operations_Superellipse.png
docs/shapes/operations_Trapezoid.png
docs/shapes/operations_Triangle.png
docs/shapes/operations_TruncGenNorm.png
docs/shapes/operations_TruncNorm.png
docs/shapes/operations_Uniform.png
docs/shapes/shapes.rst
docs/shapes/superellipse.png
docs/shapes/superellipse.rst
docs/shapes/superellipse_var.png
docs/shapes/trapezoid.png
docs/shapes/trapezoid.rst
docs/shapes/triangle.png
docs/shapes/triangle.py
phuzzy.egg-info/PKG-INFO
phuzzy.egg-info/SOURCES.txt
phuzzy.egg-info/dependency_links.txt
phuzzy.egg-info/requires.txt
phuzzy.egg-info/top_level.txt
